{
  "BurstVersion": "9b3cf96f-932a-482e-8c8c-56d5e4252662",
  "Assemblies": [
    {
      "FullName": "Unity.Burst, Version=0.0.0.0, Culture=neutral, PublicKeyToken=null",
      "FilePath": "C:\\Users\\Public\\Documents\\Unity Projects\\NetworkingGame\\Library\\ScriptAssemblies\\Unity.Burst.dll",
      "LastWriteTime": "2020-06-17T13:23:30.9820229Z"
    },
    {
      "FullName": "netstandard, Version=2.0.0.0, Culture=neutral, PublicKeyToken=cc7b13ffcd2ddd51",
      "FilePath": "C:\\Program Files\\Unity\\Hub\\Editor\\2019.3.9f1\\Editor\\Data\\MonoBleedingEdge\\lib\\mono\\unityjit\\Facades\\netstandard.dll",
      "LastWriteTime": "2020-04-07T03:41:54Z"
    },
    {
      "FullName": "mscorlib, Version=4.0.0.0, Culture=neutral, PublicKeyToken=b77a5c561934e089",
      "FilePath": "C:\\Program Files\\Unity\\Hub\\Editor\\2019.3.9f1\\Editor\\Data\\MonoBleedingEdge\\lib\\mono\\unityjit\\mscorlib.dll",
      "LastWriteTime": "2020-04-07T03:41:54Z"
    },
    {
      "FullName": "Unity.Networking.Transport, Version=0.0.0.0, Culture=neutral, PublicKeyToken=null",
      "FilePath": "C:\\Users\\Public\\Documents\\Unity Projects\\NetworkingGame\\Library\\ScriptAssemblies\\Unity.Networking.Transport.dll",
      "LastWriteTime": "2020-06-17T13:23:34.2426989Z"
    },
    {
      "FullName": "UnityEngine.CoreModule, Version=0.0.0.0, Culture=neutral, PublicKeyToken=null",
      "FilePath": "C:\\Program Files\\Unity\\Hub\\Editor\\2019.3.9f1\\Editor\\Data\\Managed\\UnityEngine\\UnityEngine.CoreModule.dll",
      "LastWriteTime": "2020-04-07T03:50:30Z"
    },
    {
      "FullName": "mscorlib, Version=2.0.0.0, Culture=neutral, PublicKeyToken=b77a5c561934e089",
      "FilePath": "C:\\Program Files\\Unity\\Hub\\Editor\\2019.3.9f1\\Editor\\Data\\MonoBleedingEdge\\lib\\mono\\unityjit\\mscorlib.dll",
      "LastWriteTime": "2020-04-07T03:41:54Z"
    },
    {
      "FullName": "Unity.Mathematics, Version=0.0.0.0, Culture=neutral, PublicKeyToken=null",
      "FilePath": "C:\\Users\\Public\\Documents\\Unity Projects\\NetworkingGame\\Library\\ScriptAssemblies\\Unity.Mathematics.dll",
      "LastWriteTime": "2020-06-17T13:23:33.1633399Z"
    },
    {
      "FullName": "Unity.Collections, Version=0.0.0.0, Culture=neutral, PublicKeyToken=null",
      "FilePath": "C:\\Users\\Public\\Documents\\Unity Projects\\NetworkingGame\\Library\\ScriptAssemblies\\Unity.Collections.dll",
      "LastWriteTime": "2020-06-17T13:23:33.9026361Z"
    }
  ],
  "Functions": [
    {
      "FullName": "System.Int32 Unity.Burst.Intrinsics.X86::DoGetCSRTrampoline()",
      "ModuleOptionsHash": 10400676583197497630,
      "ModuleHash": "5b3fb995eb1f54481cb42367227e2591",
      "LinkName": "CDCA4A5193BE5947",
      "AssemblyDependencyIndices": [
        0,
        1,
        2
      ]
    },
    {
      "FullName": "System.Void Unity.Burst.Intrinsics.X86::DoSetCSRTrampoline(System.Int32)",
      "ModuleOptionsHash": 10400676583197497630,
      "ModuleHash": "24b193651822c5f5d0c0799dba902d7f",
      "LinkName": "801E9A000BB37B05",
      "AssemblyDependencyIndices": [
        0,
        1,
        2
      ]
    },
    {
      "FullName": "System.Int32 Unity.Networking.Transport.UDPNetworkInterface::EndSendMessage(Unity.Networking.Transport.NetworkInterfaceSendHandle&,Unity.Networking.Transport.NetworkInterfaceEndPoint&,System.IntPtr,Unity.Networking.Transport.NetworkSendQueueHandle&)",
      "ModuleOptionsHash": 10400676583197497630,
      "ModuleHash": "fca6bc70cfd91716354bef7cbb97de99",
      "LinkName": "2B0D010C6271F443",
      "AssemblyDependencyIndices": [
        3,
        1,
        2
      ]
    },
    {
      "FullName": "System.Void Unity.Networking.Transport.UDPNetworkInterface::AbortSendMessage(Unity.Networking.Transport.NetworkInterfaceSendHandle&,System.IntPtr)",
      "ModuleOptionsHash": 10400676583197497630,
      "ModuleHash": "e2a70d7c7e70ba018367ca6c27ba8d15",
      "LinkName": "578FFC8DB1331D99",
      "AssemblyDependencyIndices": [
        3,
        1,
        2
      ]
    },
    {
      "FullName": "System.Int32 Unity.Networking.Transport.UDPNetworkInterface::BeginSendMessage(Unity.Networking.Transport.NetworkInterfaceSendHandle&,System.IntPtr)",
      "ModuleOptionsHash": 10400676583197497630,
      "ModuleHash": "59e3baf1654b83a930f64b17fe1c23fa",
      "LinkName": "D199FF249C8EB600",
      "AssemblyDependencyIndices": [
        3,
        1,
        2,
        4,
        5
      ]
    },
    {
      "FullName": "System.Void Unity.Networking.Transport.NullPipelineStage::Send(Unity.Networking.Transport.NetworkPipelineContext&,Unity.Networking.Transport.InboundSendBuffer&,Unity.Networking.Transport.NetworkPipelineStage/Requests&)",
      "ModuleOptionsHash": 10400676583197497630,
      "ModuleHash": "50cc68d134b89c1d4438c8b2164e4d02",
      "LinkName": "4FEA16903D1779F7",
      "AssemblyDependencyIndices": [
        3,
        1,
        2,
        4
      ]
    },
    {
      "FullName": "System.Void Unity.Networking.Transport.NullPipelineStage::Receive(Unity.Networking.Transport.NetworkPipelineContext&,Unity.Networking.Transport.InboundRecvBuffer&,Unity.Networking.Transport.NetworkPipelineStage/Requests&)",
      "ModuleOptionsHash": 10400676583197497630,
      "ModuleHash": "24caed3eb1af832262d99dea986a7c21",
      "LinkName": "51F552637D3E151F",
      "AssemblyDependencyIndices": [
        3,
        1,
        2,
        4
      ]
    },
    {
      "FullName": "System.Void Unity.Networking.Transport.NullPipelineStage::InitializeConnection(System.Byte*,System.Int32,System.Byte*,System.Int32,System.Byte*,System.Int32,System.Byte*,System.Int32)",
      "ModuleOptionsHash": 10400676583197497630,
      "ModuleHash": "7df28f41b5625d1a0a65331ab47d8132",
      "LinkName": "AB6431E798DCDD09",
      "AssemblyDependencyIndices": [
        3,
        1,
        2
      ]
    },
    {
      "FullName": "System.Void Unity.Networking.Transport.ReliableSequencedPipelineStage::Receive(Unity.Networking.Transport.NetworkPipelineContext&,Unity.Networking.Transport.InboundRecvBuffer&,Unity.Networking.Transport.NetworkPipelineStage/Requests&)",
      "ModuleOptionsHash": 10400676583197497630,
      "ModuleHash": "e77af32aa404c18b6a01d367f883157e",
      "LinkName": "90B271FA71ACEBFD",
      "AssemblyDependencyIndices": [
        3,
        1,
        2,
        4,
        5
      ]
    },
    {
      "FullName": "System.Void Unity.Networking.Transport.ReliableSequencedPipelineStage::Send(Unity.Networking.Transport.NetworkPipelineContext&,Unity.Networking.Transport.InboundSendBuffer&,Unity.Networking.Transport.NetworkPipelineStage/Requests&)",
      "ModuleOptionsHash": 10400676583197497630,
      "ModuleHash": "2a63112ae615319e9b0d59edf2904044",
      "LinkName": "6290A858D24C9591",
      "AssemblyDependencyIndices": [
        3,
        1,
        2,
        4,
        5
      ]
    },
    {
      "FullName": "System.Void Unity.Networking.Transport.ReliableSequencedPipelineStage::InitializeConnection(System.Byte*,System.Int32,System.Byte*,System.Int32,System.Byte*,System.Int32,System.Byte*,System.Int32)",
      "ModuleOptionsHash": 10400676583197497630,
      "ModuleHash": "464c6738ffb5d66996437f6a40240d46",
      "LinkName": "2F483606ED7F5C8A",
      "AssemblyDependencyIndices": [
        3,
        1,
        2,
        4,
        5
      ]
    },
    {
      "FullName": "System.Void Unity.Networking.Transport.UnreliableSequencedPipelineStage::Receive(Unity.Networking.Transport.NetworkPipelineContext&,Unity.Networking.Transport.InboundRecvBuffer&,Unity.Networking.Transport.NetworkPipelineStage/Requests&)",
      "ModuleOptionsHash": 10400676583197497630,
      "ModuleHash": "61d5ce81a1d67956d4e0b240ace28543",
      "LinkName": "4E0E2EBE8D359B89",
      "AssemblyDependencyIndices": [
        3,
        1,
        2,
        4,
        5
      ]
    },
    {
      "FullName": "System.Void Unity.Networking.Transport.UnreliableSequencedPipelineStage::Send(Unity.Networking.Transport.NetworkPipelineContext&,Unity.Networking.Transport.InboundSendBuffer&,Unity.Networking.Transport.NetworkPipelineStage/Requests&)",
      "ModuleOptionsHash": 10400676583197497630,
      "ModuleHash": "2fe586bfaeeba07d6b4b8d7c19f4a254",
      "LinkName": "858147B957D86ED6",
      "AssemblyDependencyIndices": [
        3,
        1,
        2,
        4,
        5
      ]
    },
    {
      "FullName": "System.Void Unity.Networking.Transport.UnreliableSequencedPipelineStage::InitializeConnection(System.Byte*,System.Int32,System.Byte*,System.Int32,System.Byte*,System.Int32,System.Byte*,System.Int32)",
      "ModuleOptionsHash": 10400676583197497630,
      "ModuleHash": "e411902a4504f599b6724a9f8903c898",
      "LinkName": "8BCAA01A321CA107",
      "AssemblyDependencyIndices": [
        3,
        1,
        2
      ]
    },
    {
      "FullName": "System.Void Unity.Networking.Transport.SimulatorPipelineStage::Receive(Unity.Networking.Transport.NetworkPipelineContext&,Unity.Networking.Transport.InboundRecvBuffer&,Unity.Networking.Transport.NetworkPipelineStage/Requests&)",
      "ModuleOptionsHash": 10400676583197497630,
      "ModuleHash": "685ddb26d90c150ba73fa7b153580f94",
      "LinkName": "4DB96AA94E6326F7",
      "AssemblyDependencyIndices": [
        3,
        1,
        2,
        4,
        5,
        6
      ]
    },
    {
      "FullName": "System.Void Unity.Networking.Transport.SimulatorPipelineStage::Send(Unity.Networking.Transport.NetworkPipelineContext&,Unity.Networking.Transport.InboundSendBuffer&,Unity.Networking.Transport.NetworkPipelineStage/Requests&)",
      "ModuleOptionsHash": 10400676583197497630,
      "ModuleHash": "6f048c746074c4c57365212300202e0d",
      "LinkName": "DB22BD6CD4A91D8F",
      "AssemblyDependencyIndices": [
        3,
        1,
        2,
        4
      ]
    },
    {
      "FullName": "System.Void Unity.Networking.Transport.SimulatorPipelineStage::InitializeConnection(System.Byte*,System.Int32,System.Byte*,System.Int32,System.Byte*,System.Int32,System.Byte*,System.Int32)",
      "ModuleOptionsHash": 10400676583197497630,
      "ModuleHash": "204f14da1f656795edb52042fe56dc46",
      "LinkName": "834661DA2978B91C",
      "AssemblyDependencyIndices": [
        3,
        1,
        2,
        4,
        5,
        6
      ]
    },
    {
      "FullName": "System.Void Unity.Networking.Transport.SimulatorPipelineStageInSend::Receive(Unity.Networking.Transport.NetworkPipelineContext&,Unity.Networking.Transport.InboundRecvBuffer&,Unity.Networking.Transport.NetworkPipelineStage/Requests&)",
      "ModuleOptionsHash": 10400676583197497630,
      "ModuleHash": "070cb9ea26b68529798a39d4e6b92936",
      "LinkName": "740748C929C56FB9",
      "AssemblyDependencyIndices": [
        3,
        1,
        2,
        4
      ]
    },
    {
      "FullName": "System.Void Unity.Networking.Transport.SimulatorPipelineStageInSend::Send(Unity.Networking.Transport.NetworkPipelineContext&,Unity.Networking.Transport.InboundSendBuffer&,Unity.Networking.Transport.NetworkPipelineStage/Requests&)",
      "ModuleOptionsHash": 10400676583197497630,
      "ModuleHash": "b665f080e66d1313a2372538988364b3",
      "LinkName": "F7D896FB42351B32",
      "AssemblyDependencyIndices": [
        3,
        1,
        2,
        4,
        5,
        6
      ]
    },
    {
      "FullName": "System.Void Unity.Networking.Transport.SimulatorPipelineStageInSend::InitializeConnection(System.Byte*,System.Int32,System.Byte*,System.Int32,System.Byte*,System.Int32,System.Byte*,System.Int32)",
      "ModuleOptionsHash": 10400676583197497630,
      "ModuleHash": "a57ff252bc29513b8ba3989b8857e5e7",
      "LinkName": "F4BD41705BF46512",
      "AssemblyDependencyIndices": [
        3,
        1,
        2,
        4,
        5,
        6
      ]
    },
    {
      "FullName": "System.Void Unity.Jobs.IJobExtensions/JobStruct`1<Unity.Networking.Transport.NetworkDriver/UpdateJob>::Execute(T&,System.IntPtr,System.IntPtr,Unity.Jobs.LowLevel.Unsafe.JobRanges&,System.Int32)",
      "ModuleOptionsHash": 10400676583197497630,
      "ModuleHash": "3c384ddbf99ad793ab6eaa23105d4558",
      "LinkName": "08B4350BD6936DAB",
      "AssemblyDependencyIndices": [
        4,
        3,
        5,
        1,
        2,
        0,
        7,
        6
      ]
    },
    {
      "FullName": "System.Void Unity.Jobs.IJobExtensions/JobStruct`1<Unity.Networking.Transport.UDPNetworkInterface/ReceiveJob>::Execute(T&,System.IntPtr,System.IntPtr,Unity.Jobs.LowLevel.Unsafe.JobRanges&,System.Int32)",
      "ModuleOptionsHash": 10400676583197497630,
      "ModuleHash": "31014d7b57f554324d67c9b182184f7b",
      "LinkName": "C481773F4D6E4340",
      "AssemblyDependencyIndices": [
        4,
        3,
        5,
        1,
        2,
        0,
        7,
        6
      ]
    }
  ]
}